onedani/__init__.py
onedani/animation.py
onedani-0.1.dist-info/LICENSE
onedani-0.1.dist-info/METADATA
onedani-0.1.dist-info/WHEEL
onedani-0.1.dist-info/top_level.txt
onedani-0.1.dist-info/RECORD
