Metadata-Version: 2.1
Name: onedani
Version: 0.1
Summary: A package to convert your Jupyter Notebook
Home-page: https://gitlab.com/theochri/onedani
Author: Theo Christiaanse
Author-email: theochristiaanse@gmail.com
License: UNKNOWN
Platform: UNKNOWN
Classifier: Programming Language :: Python :: 3.7
Classifier: License :: OSI Approved :: MIT License
Requires-Dist: ipython (>=6)
Requires-Dist: nbformat (>=4)
Requires-Dist: nbconvert (>=5)
Requires-Dist: requests (>=2)
